nilai_py/__init__.py
nilai_py/client.py
nilai_py/common.py
nilai_py/niltypes.py
nilai_py/py.typed
nilai_py/server.py
nilai_py-0.1.2.dist-info/METADATA
nilai_py-0.1.2.dist-info/WHEEL
nilai_py-0.1.2.dist-info/RECORD
