Metadata-Version: 2.4
Name: nilai-py
Version: 0.1.2
Summary: Nilai Python SDK
Author-email: José Cabrero-Holgueras <jose.cabrero@nillion.com>
Requires-Python: >=3.10
Requires-Dist: httpx>=0.28.1
Requires-Dist: nuc>=0.1.0
Requires-Dist: openai>=1.93.0
Requires-Dist: pydantic>=2.11.7
Requires-Dist: python-dotenv>=1.1.1
